{
  "project_info": {
    "project_number": "56119157558",
    "project_id": "eazybooking-ee4d0",
    "storage_bucket": "eazybooking-ee4d0.appspot.com"
  },
  "client": [
    {
      "client_info": {
        "mobilesdk_app_id": "1:56119157558:android:2f6737c54f99659c400997",
        "android_client_info": {
          "package_name": "com.booble.eazybooking"
        }
      },
      "oauth_client": [
        {
          "client_id": "56119157558-le0vodpfctoilu0ik3ps7ti30tkct3sb.apps.googleusercontent.com",
          "client_type": 1,
          "android_info": {
            "package_name": "com.booble.eazybooking",
            "certificate_hash": "59201d3af3fbb92b996962cd2363b59ee20d2723"
          }
        },
        {
          "client_id": "56119157558-1lbmnnjj7lmjcqk0jhk2i0pb35m11uq2.apps.googleusercontent.com",
          "client_type": 3
        }
      ],
      "api_key": [
        {
          "current_key": "AIzaSyDZ-ogFTkrXkddZviHkgURNawVkVVwpHbc"
        }
      ],
      "services": {
        "appinvite_service": {
          "other_platform_oauth_client": [
            {
              "client_id": "56119157558-1lbmnnjj7lmjcqk0jhk2i0pb35m11uq2.apps.googleusercontent.com",
              "client_type": 3
            }
          ]
        }
      }
    },
    {
      "client_info": {
        "mobilesdk_app_id": "1:56119157558:android:0a802b725ee93d0d400997",
        "android_client_info": {
          "package_name": "com.booble.eazybooking.mitra"
        }
      },
      "oauth_client": [
        {
          "client_id": "56119157558-6ghd8ig5hje9v6laq492jj093717vo4o.apps.googleusercontent.com",
          "client_type": 1,
          "android_info": {
            "package_name": "com.booble.eazybooking.mitra",
            "certificate_hash": "59201d3af3fbb92b996962cd2363b59ee20d2723"
          }
        },
        {
          "client_id": "56119157558-1lbmnnjj7lmjcqk0jhk2i0pb35m11uq2.apps.googleusercontent.com",
          "client_type": 3
        }
      ],
      "api_key": [
        {
          "current_key": "AIzaSyDZ-ogFTkrXkddZviHkgURNawVkVVwpHbc"
        }
      ],
      "services": {
        "appinvite_service": {
          "other_platform_oauth_client": [
            {
              "client_id": "56119157558-1lbmnnjj7lmjcqk0jhk2i0pb35m11uq2.apps.googleusercontent.com",
              "client_type": 3
            }
          ]
        }
      }
    }
  ],
  "configuration_version": "1"
}